LICENSE.txt
MANIFEST.in
README.md
setup.py
maps/__init__.py
maps/fixedkeymap.py
maps/frozenmap.py
maps/nameddict.py
maps/namedfixedkeymap.py
maps/namedfrozenmap.py
maps/utils.py
maps.egg-info/PKG-INFO
maps.egg-info/SOURCES.txt
maps.egg-info/dependency_links.txt
maps.egg-info/requires.txt
maps.egg-info/top_level.txt