Metadata-Version: 1.1
Name: maps
Version: 5.0.0
Summary: Maps: flavors of Python dictionaries
Home-page: https://github.com/pcattori/maps
Author: Pedro Cattori
Author-email: pcattori@gmail.com
License: MIT
Keywords: maps,namddict,frozendict,fixedkey,fixeddict
Platform: UNKNOWN
Classifier: Development Status :: 5 - Production/Stable
Classifier: Intended Audience :: Developers
Classifier: License :: OSI Approved :: MIT License
Classifier: Programming Language :: Python
Classifier: Programming Language :: Python :: 2.7
Classifier: Programming Language :: Python :: 3.4
Classifier: Programming Language :: Python :: 3.5
Classifier: Programming Language :: Python :: 3.6
